yta_numpy/__init__.py
yta_numpy/audio/__init__.py
yta_numpy/audio/utils.py
yta_numpy/converter.py
yta_numpy/rgba/__init__.py
yta_numpy/rgba/combinator.py
yta_numpy/rgba/generator.py
yta_numpy/rgba/resizer.py
yta_numpy/rgba/utils.py
yta_numpy/utils.py
yta_numpy/video/__init__.py
yta_numpy/video/moviepy/__init__.py
yta_numpy/video/moviepy/frame_handler.py
yta_numpy/video/moviepy/utils.py
yta_numpy-0.0.25.dist-info/licenses/LICENSE
yta_numpy-0.0.25.dist-info/METADATA
yta_numpy-0.0.25.dist-info/WHEEL
yta_numpy-0.0.25.dist-info/RECORD
